Metadata-Version: 2.1
Name: geodemov2
Version: 0.0.1
Summary: example geo python packages
Home-page: https://github.com/Hamilton97/geodemov2
Author: Ryan Hamilton
Author-email: ryangilberthamilton@gmail.com
License: MIT license
Keywords: geodemov2
Classifier: Intended Audience :: Developers
Classifier: License :: OSI Approved :: MIT License
Classifier: Natural Language :: English
Classifier: Programming Language :: Python :: 3
Classifier: Programming Language :: Python :: 3.8
Classifier: Programming Language :: Python :: 3.9
Classifier: Programming Language :: Python :: 3.10
Classifier: Programming Language :: Python :: 3.11
Requires-Python: >=3.8
License-File: LICENSE
